odoo/addons/invader_payment_sale/README.rst
odoo/addons/invader_payment_sale/__init__.py
odoo/addons/invader_payment_sale/__manifest__.py
odoo/addons/invader_payment_sale/i18n/invader_payment_sale.pot
odoo/addons/invader_payment_sale/models/__init__.py
odoo/addons/invader_payment_sale/models/payment_transaction.py
odoo/addons/invader_payment_sale/models/sale_order.py
odoo/addons/invader_payment_sale/readme/CONTRIBUTORS.rst
odoo/addons/invader_payment_sale/readme/DESCRIPTION.rst
odoo/addons/invader_payment_sale/static/description/index.html
odoo14_addon_invader_payment_sale-14.0.1.0.1.dist-info/METADATA
odoo14_addon_invader_payment_sale-14.0.1.0.1.dist-info/WHEEL
odoo14_addon_invader_payment_sale-14.0.1.0.1.dist-info/top_level.txt
odoo14_addon_invader_payment_sale-14.0.1.0.1.dist-info/RECORD
